<?xml version="1.0" encoding="utf-8" ?>
<dwsync>
<file name="scroll_pane_inactiv.png" server="ftp.themefuse.com//demo/html/FreshFolio/" local="129419298960000000" remote="129441583800000000" />
<file name="temp_img_big_1.jpg" server="ftp.themefuse.com//demo/html/FreshFolio/" local="129439700545400000" remote="129441583800000000" />
<file name="temp_img_big_2.jpg" server="ftp.themefuse.com//demo/html/FreshFolio/" local="129439708919290000" remote="129441583800000000" />
<file name="temp_img_big_3.jpg" server="ftp.themefuse.com//demo/html/FreshFolio/" local="129439702877090000" remote="129441583800000000" />
<file name="temp_img_big_4.jpg" server="ftp.themefuse.com//demo/html/FreshFolio/" local="129439707683920000" remote="129441583800000000" />
<file name="temp_img_big_5.jpg" server="ftp.themefuse.com//demo/html/FreshFolio/" local="129439707683920000" remote="129441583800000000" />
<file name="temp_img_med_1.jpg" server="ftp.themefuse.com//demo/html/FreshFolio/" local="129439710980620000" remote="129441583800000000" />
<file name="temp_img_med_2.jpg" server="ftp.themefuse.com//demo/html/FreshFolio/" local="129439713448730000" remote="129441583800000000" />
<file name="temp_img_med_3.jpg" server="ftp.themefuse.com//demo/html/FreshFolio/" local="129439712867200000" remote="129441583800000000" />
<file name="temp_img_med_4.jpg" server="ftp.themefuse.com//demo/html/FreshFolio/" local="129439713805030000" remote="129441583800000000" />
<file name="temp_img_med_5.jpg" server="ftp.themefuse.com//demo/html/FreshFolio/" local="129439714362650000" remote="129441583800000000" />
<file name="temp_img_med_6.jpg" server="ftp.themefuse.com//demo/html/FreshFolio/" local="129439715318050000" remote="129441583800000000" />
<file name="temp_project_1.jpg" server="ftp.themefuse.com//demo/html/FreshFolio/" local="129439720090080000" remote="129441583800000000" />
<file name="temp_thumb_1.jpg" server="ftp.themefuse.com//demo/html/FreshFolio/" local="129439721603050000" remote="129441583800000000" />
<file name="temp_thumb_2.jpg" server="ftp.themefuse.com//demo/html/FreshFolio/" local="129439723001840000" remote="129441583800000000" />
<file name="temp_thumb_3.jpg" server="ftp.themefuse.com//demo/html/FreshFolio/" local="129439727351520000" remote="129441583800000000" />
<file name="temp_thumb_4.jpg" server="ftp.themefuse.com//demo/html/FreshFolio/" local="129439723639810000" remote="129441584400000000" />
<file name="temp_thumb_5.jpg" server="ftp.themefuse.com//demo/html/FreshFolio/" local="129439728884640000" remote="129441584400000000" />
<file name="temp_thumb_6.jpg" server="ftp.themefuse.com//demo/html/FreshFolio/" local="129439726780800000" remote="129441584400000000" />
</dwsync>